praisonaibench/__init__.py
praisonaibench/agent.py
praisonaibench/base_evaluator.py
praisonaibench/bench.py
praisonaibench/cli.py
praisonaibench/cost_tracker.py
praisonaibench/enhanced_report.py
praisonaibench/hybrid_evaluator.py
praisonaibench/plugin_manager.py
praisonaibench/report_generator.py
praisonaibench/report_generator_simple.py
praisonaibench/simple_evaluator.py
praisonaibench/svg_report.py
praisonaibench/version.py
praisonaibench/evaluators/__init__.py
praisonaibench/evaluators/html_evaluator.py
praisonaibench/evaluators/svg_evaluator.py
praisonaibench-0.1.1.dist-info/METADATA
praisonaibench-0.1.1.dist-info/WHEEL
praisonaibench-0.1.1.dist-info/entry_points.txt
praisonaibench-0.1.1.dist-info/RECORD
