Metadata-Version: 2.4
Name: praisonaibench
Version: 0.1.1
Summary: Simple LLM Benchmarking Tool using PraisonAI Agents
Project-URL: Homepage, https://github.com/MervinPraison/praisonaibench
Project-URL: Repository, https://github.com/MervinPraison/praisonaibench
Project-URL: Documentation, https://github.com/MervinPraison/praisonaibench#readme
Project-URL: Issues, https://github.com/MervinPraison/praisonaibench/issues
Author: MervinPraison
Maintainer: MervinPraison
License: MIT
Keywords: agents,ai,benchmark,llm,testing
Classifier: Development Status :: 4 - Beta
Classifier: Intended Audience :: Developers
Classifier: License :: OSI Approved :: MIT License
Classifier: Operating System :: OS Independent
Classifier: Programming Language :: Python :: 3
Classifier: Programming Language :: Python :: 3.8
Classifier: Programming Language :: Python :: 3.9
Classifier: Programming Language :: Python :: 3.10
Classifier: Programming Language :: Python :: 3.11
Classifier: Programming Language :: Python :: 3.12
Classifier: Topic :: Scientific/Engineering :: Artificial Intelligence
Classifier: Topic :: Software Development :: Libraries :: Python Modules
Requires-Python: >=3.8
Requires-Dist: praisonaiagents[llm]>=0.0.1
Requires-Dist: pyyaml>=6.0
Provides-Extra: all
Requires-Dist: black>=22.0; extra == 'all'
Requires-Dist: duckduckgo-search>=3.0; extra == 'all'
Requires-Dist: flake8>=4.0; extra == 'all'
Requires-Dist: mypy>=1.0; extra == 'all'
Requires-Dist: pre-commit>=3.0; extra == 'all'
Requires-Dist: pytest>=7.0; extra == 'all'
Provides-Extra: dev
Requires-Dist: black>=22.0; extra == 'dev'
Requires-Dist: flake8>=4.0; extra == 'dev'
Requires-Dist: mypy>=1.0; extra == 'dev'
Requires-Dist: pre-commit>=3.0; extra == 'dev'
Requires-Dist: pytest>=7.0; extra == 'dev'
Provides-Extra: tools
Requires-Dist: duckduckgo-search>=3.0; extra == 'tools'
